{
    "packages": {
        "swissup/argento-breeze": [
            {
                "name": "swissup/argento-breeze",
                "version": "1.0.0",
                "version_normalized": "1.0.0.0",
                "source": {
                    "type": "git",
                    "url": "git@github.com:swissup/argento-breeze.git",
                    "reference": "a1d5026233cbd73aa859a943c6969e46a6ad2dd5"
                },
                "dist": {
                    "type": "zip",
                    "url": "https://api.github.com/repos/swissup/argento-breeze/zipball/a1d5026233cbd73aa859a943c6969e46a6ad2dd5",
                    "reference": "a1d5026233cbd73aa859a943c6969e46a6ad2dd5",
                    "shasum": ""
                },
                "require": {
                    "swissup/module-ajaxpro": "^1.6.5",
                    "swissup/module-ajaxsearch": "^1.11.22",
                    "swissup/module-amp": "^1.5.2",
                    "swissup/module-askit": "^1.11.6",
                    "swissup/module-attributepages": "^1.5.1",
                    "swissup/module-breeze": "^1.12.0",
                    "swissup/module-compare": "^1.1.3",
                    "swissup/module-easy-slide": "^1.6.27",
                    "swissup/module-easybanner": "^1.8.3",
                    "swissup/module-easycatalogimg": "^1.4.21",
                    "swissup/module-easytabs": "^1.10.4",
                    "swissup/module-fblike": "^1.3.6",
                    "swissup/module-featured-attributes": "^1.1.6",
                    "swissup/module-gdpr": "^1.5.5",
                    "swissup/module-gdpr-askit": "^1.1.3",
                    "swissup/module-gdpr-reviewreminder": "^1.0.0",
                    "swissup/module-gdpr-testimonials": "^1.1.1",
                    "swissup/module-highlight": "^1.7.28",
                    "swissup/module-hover-gallery": "^1.3.10",
                    "swissup/module-hreflang": "^1.4.11",
                    "swissup/module-navigationpro": "^1.16.14",
                    "swissup/module-pagespeed": "^1.5.7",
                    "swissup/module-pro-labels": "^1.6.20",
                    "swissup/module-quantity-switcher": "^1.1.14",
                    "swissup/module-reviewreminder": "^1.1.10",
                    "swissup/module-rich-snippets": "^1.4.19",
                    "swissup/module-seo-canonical": "^1.11.6",
                    "swissup/module-seo-core": "^1.3.7",
                    "swissup/module-seo-cross-links": "^1.1.6",
                    "swissup/module-seo-html-sitemap": "^1.1.12",
                    "swissup/module-seo-images": "^1.3.15",
                    "swissup/module-seo-pager": "^1.2.9",
                    "swissup/module-seo-templates": "^1.6.3",
                    "swissup/module-seo-urls": "^1.5.32",
                    "swissup/module-seo-xml-sitemap": "^1.1.11",
                    "swissup/module-sold-together": "^1.8.4",
                    "swissup/module-testimonials": "^1.3.2",
                    "swissup/theme-frontend-argentobreeze-blank": "^1.0.0",
                    "swissup/theme-frontend-argentobreeze-stripes": "^1.0.0"
                },
                "time": "2022-06-17T14:22:39+00:00",
                "type": "metapackage",
                "extra": {
                    "marketplace": {
                        "gallery": [
                            "https://docs.swissuplabs.com/images/marketplace/theme-frontend-argento.png"
                        ],
                        "links": {
                            "docs": "https://docs.swissuplabs.com/m2/argento-breeze/",
                            "changelog": "https://docs.swissuplabs.com/m2/argento-breeze/changelog/"
                        }
                    }
                },
                "license": [
                    "OSL-3.0"
                ],
                "description": "Argento Breeze Themes",
                "support": {
                    "source": "https://github.com/swissup/argento-breeze/tree/1.0.0",
                    "issues": "https://github.com/swissup/argento-breeze/issues"
                }
            },
            {
                "name": "swissup/argento-breeze",
                "version": "1.0.1",
                "version_normalized": "1.0.1.0",
                "source": {
                    "type": "git",
                    "url": "git@github.com:swissup/argento-breeze.git",
                    "reference": "b7a9a06f62769a3e2f1bfb53190b7cc47c620f61"
                },
                "dist": {
                    "type": "zip",
                    "url": "https://api.github.com/repos/swissup/argento-breeze/zipball/b7a9a06f62769a3e2f1bfb53190b7cc47c620f61",
                    "reference": "b7a9a06f62769a3e2f1bfb53190b7cc47c620f61",
                    "shasum": ""
                },
                "require": {
                    "swissup/module-ajaxpro": "^1.6.5",
                    "swissup/module-ajaxsearch": "^1.11.22",
                    "swissup/module-amp": "^1.5.2",
                    "swissup/module-askit": "^1.11.6",
                    "swissup/module-attributepages": "^1.5.1",
                    "swissup/module-breeze": "^1.12.1",
                    "swissup/module-compare": "^1.1.3",
                    "swissup/module-easy-slide": "^1.6.27",
                    "swissup/module-easybanner": "^1.8.3",
                    "swissup/module-easycatalogimg": "^1.4.21",
                    "swissup/module-easytabs": "^1.10.4",
                    "swissup/module-fblike": "^1.3.6",
                    "swissup/module-featured-attributes": "^1.1.6",
                    "swissup/module-gdpr": "^1.5.5",
                    "swissup/module-gdpr-askit": "^1.1.3",
                    "swissup/module-gdpr-reviewreminder": "^1.0.0",
                    "swissup/module-gdpr-testimonials": "^1.1.1",
                    "swissup/module-highlight": "^1.7.28",
                    "swissup/module-hover-gallery": "^1.3.10",
                    "swissup/module-hreflang": "^1.4.11",
                    "swissup/module-navigationpro": "^1.16.14",
                    "swissup/module-pagespeed": "^1.5.7",
                    "swissup/module-pro-labels": "^1.6.20",
                    "swissup/module-quantity-switcher": "^1.1.14",
                    "swissup/module-reviewreminder": "^1.1.10",
                    "swissup/module-rich-snippets": "^1.4.19",
                    "swissup/module-seo-canonical": "^1.11.6",
                    "swissup/module-seo-core": "^1.3.7",
                    "swissup/module-seo-cross-links": "^1.1.6",
                    "swissup/module-seo-html-sitemap": "^1.1.12",
                    "swissup/module-seo-images": "^1.3.15",
                    "swissup/module-seo-pager": "^1.2.9",
                    "swissup/module-seo-templates": "^1.6.3",
                    "swissup/module-seo-urls": "^1.5.32",
                    "swissup/module-seo-xml-sitemap": "^1.1.11",
                    "swissup/module-sold-together": "^1.8.4",
                    "swissup/module-testimonials": "^1.3.2",
                    "swissup/theme-frontend-argentobreeze-blank": "^1.0.0",
                    "swissup/theme-frontend-argentobreeze-stripes": "^1.0.1"
                },
                "time": "2022-06-20T11:28:10+00:00",
                "type": "metapackage",
                "extra": {
                    "marketplace": {
                        "gallery": [
                            "https://docs.swissuplabs.com/images/marketplace/theme-frontend-argento.png"
                        ],
                        "links": {
                            "docs": "https://docs.swissuplabs.com/m2/argento-breeze/",
                            "changelog": "https://docs.swissuplabs.com/m2/argento-breeze/changelog/"
                        }
                    }
                },
                "license": [
                    "OSL-3.0"
                ],
                "description": "Argento Breeze Themes",
                "support": {
                    "source": "https://github.com/swissup/argento-breeze/tree/1.0.1",
                    "issues": "https://github.com/swissup/argento-breeze/issues"
                }
            },
            {
                "name": "swissup/argento-breeze",
                "version": "1.0.2",
                "version_normalized": "1.0.2.0",
                "source": {
                    "type": "git",
                    "url": "git@github.com:swissup/argento-breeze.git",
                    "reference": "3fe2d81ba67cc88a96ba5698e57ceca2d8053bff"
                },
                "dist": {
                    "type": "zip",
                    "url": "https://api.github.com/repos/swissup/argento-breeze/zipball/3fe2d81ba67cc88a96ba5698e57ceca2d8053bff",
                    "reference": "3fe2d81ba67cc88a96ba5698e57ceca2d8053bff",
                    "shasum": ""
                },
                "require": {
                    "swissup/module-ajaxpro": "^1.6.7",
                    "swissup/module-ajaxsearch": "^1.11.23",
                    "swissup/module-amp": "^1.5.2",
                    "swissup/module-askit": "^1.11.6",
                    "swissup/module-attributepages": "^1.5.2",
                    "swissup/module-breeze": "^1.13.4",
                    "swissup/module-compare": "^1.1.3",
                    "swissup/module-easy-slide": "^1.6.27",
                    "swissup/module-easybanner": "^1.8.4",
                    "swissup/module-easycatalogimg": "^1.4.21",
                    "swissup/module-easytabs": "^1.10.4",
                    "swissup/module-fblike": "^1.3.6",
                    "swissup/module-featured-attributes": "^1.1.6",
                    "swissup/module-gdpr": "^1.5.5",
                    "swissup/module-gdpr-askit": "^1.1.3",
                    "swissup/module-gdpr-reviewreminder": "^1.0.0",
                    "swissup/module-gdpr-testimonials": "^1.1.1",
                    "swissup/module-highlight": "^1.7.30",
                    "swissup/module-hover-gallery": "^1.3.10",
                    "swissup/module-hreflang": "^1.4.11",
                    "swissup/module-navigationpro": "^1.16.14",
                    "swissup/module-pagespeed": "^1.5.7",
                    "swissup/module-pro-labels": "^1.6.20",
                    "swissup/module-quantity-switcher": "^1.1.14",
                    "swissup/module-reviewreminder": "^1.1.10",
                    "swissup/module-rich-snippets": "^1.4.19",
                    "swissup/module-seo-canonical": "^1.11.6",
                    "swissup/module-seo-core": "^1.3.7",
                    "swissup/module-seo-cross-links": "^1.1.6",
                    "swissup/module-seo-html-sitemap": "^1.1.12",
                    "swissup/module-seo-images": "^1.3.15",
                    "swissup/module-seo-pager": "^1.2.9",
                    "swissup/module-seo-templates": "^1.6.3",
                    "swissup/module-seo-urls": "^1.5.32",
                    "swissup/module-seo-xml-sitemap": "^1.1.11",
                    "swissup/module-sold-together": "^1.8.5",
                    "swissup/module-testimonials": "^1.3.2",
                    "swissup/theme-frontend-argentobreeze-blank": "^1.0.2",
                    "swissup/theme-frontend-argentobreeze-stripes": "^1.0.4"
                },
                "time": "2022-07-19T06:47:24+00:00",
                "type": "metapackage",
                "extra": {
                    "marketplace": {
                        "gallery": [
                            "https://docs.swissuplabs.com/images/marketplace/theme-frontend-argento.png"
                        ],
                        "links": {
                            "docs": "https://docs.swissuplabs.com/m2/argento-breeze/",
                            "changelog": "https://docs.swissuplabs.com/m2/argento-breeze/changelog/"
                        }
                    }
                },
                "license": [
                    "OSL-3.0"
                ],
                "description": "Argento Breeze Themes",
                "support": {
                    "source": "https://github.com/swissup/argento-breeze/tree/1.0.2",
                    "issues": "https://github.com/swissup/argento-breeze/issues"
                }
            },
            {
                "name": "swissup/argento-breeze",
                "version": "2.0.0",
                "version_normalized": "2.0.0.0",
                "source": {
                    "type": "git",
                    "url": "git@github.com:swissup/argento-breeze.git",
                    "reference": "83b800a64de1519cd02643e725280137429c5e26"
                },
                "dist": {
                    "type": "zip",
                    "url": "https://api.github.com/repos/swissup/argento-breeze/zipball/83b800a64de1519cd02643e725280137429c5e26",
                    "reference": "83b800a64de1519cd02643e725280137429c5e26",
                    "shasum": ""
                },
                "require": {
                    "swissup/module-ajaxpro": "^1.6.15",
                    "swissup/module-ajaxsearch": "^1.13.1",
                    "swissup/module-amp": "^1.5.3",
                    "swissup/module-askit": "^1.12.7",
                    "swissup/module-attributepages": "^1.5.2",
                    "swissup/module-breeze": "^2.0.0",
                    "swissup/module-breeze-integrations": "^1.2.7",
                    "swissup/module-compare": "^1.1.3",
                    "swissup/module-easy-slide": "^1.6.27",
                    "swissup/module-easybanner": "^1.9.2",
                    "swissup/module-easycatalogimg": "^1.4.23",
                    "swissup/module-easytabs": "^1.11.1",
                    "swissup/module-fblike": "^1.3.7",
                    "swissup/module-featured-attributes": "^1.1.6",
                    "swissup/module-gdpr": "^1.5.9",
                    "swissup/module-gdpr-askit": "^1.1.3",
                    "swissup/module-gdpr-reviewreminder": "^1.0.0",
                    "swissup/module-gdpr-testimonials": "^1.1.1",
                    "swissup/module-highlight": "^1.8.4",
                    "swissup/module-hover-gallery": "^1.3.11",
                    "swissup/module-hreflang": "^1.5.2",
                    "swissup/module-navigationpro": "^1.16.17",
                    "swissup/module-pagespeed": "^1.6.0",
                    "swissup/module-pro-labels": "^1.6.21",
                    "swissup/module-quantity-switcher": "^1.1.16",
                    "swissup/module-reviewreminder": "^1.1.13",
                    "swissup/module-rich-snippets": "^1.4.20",
                    "swissup/module-seo-canonical": "^1.11.6",
                    "swissup/module-seo-core": "^1.3.7",
                    "swissup/module-seo-cross-links": "^1.1.7",
                    "swissup/module-seo-html-sitemap": "^1.1.14",
                    "swissup/module-seo-images": "^1.3.16",
                    "swissup/module-seo-pager": "^1.2.9",
                    "swissup/module-seo-templates": "^1.6.3",
                    "swissup/module-seo-urls": "^1.5.36",
                    "swissup/module-seo-xml-sitemap": "^1.1.13",
                    "swissup/module-sold-together": "^1.8.8",
                    "swissup/module-testimonials": "^1.3.3",
                    "swissup/theme-frontend-argentobreeze-blank": "^2.0.0",
                    "swissup/theme-frontend-argentobreeze-force": "^2.0.0",
                    "swissup/theme-frontend-argentobreeze-stripes": "^2.0.0"
                },
                "time": "2022-11-15T13:25:17+00:00",
                "type": "metapackage",
                "extra": {
                    "marketplace": {
                        "gallery": [
                            "https://docs.swissuplabs.com/images/marketplace/theme-frontend-argento.png"
                        ],
                        "links": {
                            "docs": "https://docs.swissuplabs.com/m2/argento-breeze/",
                            "changelog": "https://docs.swissuplabs.com/m2/argento-breeze/changelog/"
                        }
                    }
                },
                "license": [
                    "OSL-3.0"
                ],
                "description": "Argento Breeze Themes",
                "support": {
                    "source": "https://github.com/swissup/argento-breeze/tree/2.0.0",
                    "issues": "https://github.com/swissup/argento-breeze/issues"
                }
            },
            {
                "name": "swissup/argento-breeze",
                "version": "2.1.0",
                "version_normalized": "2.1.0.0",
                "source": {
                    "type": "git",
                    "url": "git@github.com:swissup/argento-breeze.git",
                    "reference": "28615a36e50cb934e7e244d03604786b50287c99"
                },
                "dist": {
                    "type": "zip",
                    "url": "https://api.github.com/repos/swissup/argento-breeze/zipball/28615a36e50cb934e7e244d03604786b50287c99",
                    "reference": "28615a36e50cb934e7e244d03604786b50287c99",
                    "shasum": ""
                },
                "require": {
                    "swissup/module-ajaxpro": "^1.6.28",
                    "swissup/module-ajaxsearch": "^1.13.12",
                    "swissup/module-amp": "^1.5.6",
                    "swissup/module-askit": "^1.13.0",
                    "swissup/module-attributepages": "^1.6.4",
                    "swissup/module-breeze": "^2.8.5",
                    "swissup/module-breeze-integrations": "^1.3.1",
                    "swissup/module-chat-gpt-assistant": "^1.0.1",
                    "swissup/module-compare": "^1.2.1",
                    "swissup/module-easy-slide": "^1.8.1",
                    "swissup/module-easybanner": "^1.9.10",
                    "swissup/module-easycatalogimg": "^1.5.0",
                    "swissup/module-easytabs": "^1.12.0",
                    "swissup/module-fblike": "^1.3.8",
                    "swissup/module-featured-attributes": "^1.1.7",
                    "swissup/module-gdpr": "^1.5.18",
                    "swissup/module-gdpr-askit": "^1.1.3",
                    "swissup/module-gdpr-reviewreminder": "^1.0.0",
                    "swissup/module-gdpr-testimonials": "^1.1.1",
                    "swissup/module-highlight": "^1.8.10",
                    "swissup/module-hover-gallery": "^1.3.11",
                    "swissup/module-hreflang": "^1.6.2",
                    "swissup/module-hreflang-import-export": "^1.0.1",
                    "swissup/module-navigationpro": "^1.17.2",
                    "swissup/module-pagespeed": "^1.7.8",
                    "swissup/module-pro-labels": "^1.7.3",
                    "swissup/module-pro-labels-configurable-product": "^1.0.1",
                    "swissup/module-quantity-switcher": "^1.1.19",
                    "swissup/module-reviewreminder": "^1.1.14",
                    "swissup/module-rich-snippets": "^1.7.0",
                    "swissup/module-seo-canonical": "^1.11.8",
                    "swissup/module-seo-core": "^1.3.9",
                    "swissup/module-seo-cross-links": "^1.1.12",
                    "swissup/module-seo-html-sitemap": "^1.1.16",
                    "swissup/module-seo-images": "^1.3.19",
                    "swissup/module-seo-pager": "^1.3.3",
                    "swissup/module-seo-templates": "^1.7.5",
                    "swissup/module-seo-urls": "^1.5.44",
                    "swissup/module-seo-xml-sitemap": "^1.1.15",
                    "swissup/module-sold-together": "^1.9.8",
                    "swissup/module-sold-together-email": "^1.0.0",
                    "swissup/module-sold-together-import-export": "^1.0.1",
                    "swissup/module-testimonials": "^1.3.9",
                    "swissup/theme-frontend-argentobreeze-blank": "^2.0.2",
                    "swissup/theme-frontend-argentobreeze-force": "^2.0.4",
                    "swissup/theme-frontend-argentobreeze-stripes": "^2.0.1"
                },
                "time": "2023-07-27T12:49:13+00:00",
                "type": "metapackage",
                "extra": {
                    "marketplace": {
                        "gallery": [
                            "https://docs.swissuplabs.com/images/marketplace/theme-frontend-argento.png"
                        ],
                        "links": {
                            "docs": "https://docs.swissuplabs.com/m2/argento-breeze/",
                            "changelog": "https://docs.swissuplabs.com/m2/argento-breeze/changelog/"
                        }
                    }
                },
                "license": [
                    "OSL-3.0"
                ],
                "description": "Argento Breeze Themes",
                "support": {
                    "source": "https://github.com/swissup/argento-breeze/tree/2.1.0",
                    "issues": "https://github.com/swissup/argento-breeze/issues"
                }
            },
            {
                "name": "swissup/argento-breeze",
                "version": "2.2.0",
                "version_normalized": "2.2.0.0",
                "source": {
                    "type": "git",
                    "url": "git@github.com:swissup/argento-breeze.git",
                    "reference": "8a8f41618f120e8056113e861b9d17955a58e6f6"
                },
                "dist": {
                    "type": "zip",
                    "url": "https://api.github.com/repos/swissup/argento-breeze/zipball/8a8f41618f120e8056113e861b9d17955a58e6f6",
                    "reference": "8a8f41618f120e8056113e861b9d17955a58e6f6",
                    "shasum": ""
                },
                "require": {
                    "swissup/module-ajaxpro": "^1.6.34",
                    "swissup/module-ajaxsearch": "^1.13.15",
                    "swissup/module-amp": "^1.5.7",
                    "swissup/module-askit": "^1.13.3",
                    "swissup/module-attributepages": "^1.6.7",
                    "swissup/module-breeze": "^2.11.0",
                    "swissup/module-breeze-integrations": "^1.3.1",
                    "swissup/module-chat-gpt-assistant": "^1.0.1",
                    "swissup/module-compare": "^1.2.1",
                    "swissup/module-easy-slide": "^1.8.4",
                    "swissup/module-easybanner": "^1.9.13",
                    "swissup/module-easycatalogimg": "^1.5.2",
                    "swissup/module-easytabs": "^1.12.7",
                    "swissup/module-fblike": "^1.3.8",
                    "swissup/module-featured-attributes": "^1.1.7",
                    "swissup/module-gdpr": "^1.5.20",
                    "swissup/module-gdpr-askit": "^1.1.3",
                    "swissup/module-gdpr-reviewreminder": "^1.0.0",
                    "swissup/module-gdpr-testimonials": "^1.1.1",
                    "swissup/module-highlight": "^1.8.11",
                    "swissup/module-hover-gallery": "^1.3.11",
                    "swissup/module-hreflang": "^1.6.4",
                    "swissup/module-hreflang-import-export": "^1.0.1",
                    "swissup/module-navigationpro": "^1.17.7",
                    "swissup/module-pagespeed": "^1.7.20",
                    "swissup/module-pro-labels": "^1.7.5",
                    "swissup/module-pro-labels-configurable-product": "^1.0.1",
                    "swissup/module-quantity-switcher": "^1.1.19",
                    "swissup/module-reviewreminder": "^1.1.15",
                    "swissup/module-rich-snippets": "^1.7.1",
                    "swissup/module-seo-canonical": "^1.11.8",
                    "swissup/module-seo-core": "^1.3.9",
                    "swissup/module-seo-cross-links": "^1.1.12",
                    "swissup/module-seo-html-sitemap": "^1.1.17",
                    "swissup/module-seo-images": "^1.3.20",
                    "swissup/module-seo-pager": "^1.3.3",
                    "swissup/module-seo-templates": "^1.7.5",
                    "swissup/module-seo-urls": "^1.5.48",
                    "swissup/module-seo-xml-sitemap": "^1.1.15",
                    "swissup/module-sold-together": "^1.9.11",
                    "swissup/module-sold-together-email": "^1.0.0",
                    "swissup/module-sold-together-import-export": "^1.0.1",
                    "swissup/module-testimonials": "^1.3.10",
                    "swissup/theme-frontend-argentobreeze-blank": "^2.1.0",
                    "swissup/theme-frontend-argentobreeze-chic": "^2.0.0",
                    "swissup/theme-frontend-argentobreeze-force": "^2.0.8",
                    "swissup/theme-frontend-argentobreeze-stripes": "^2.0.3"
                },
                "time": "2023-11-28T10:13:02+00:00",
                "type": "metapackage",
                "extra": {
                    "marketplace": {
                        "gallery": [
                            "https://docs.swissuplabs.com/images/marketplace/theme-frontend-argento.png"
                        ],
                        "links": {
                            "docs": "https://docs.swissuplabs.com/m2/argento-breeze/",
                            "changelog": "https://docs.swissuplabs.com/m2/argento-breeze/changelog/"
                        }
                    }
                },
                "license": [
                    "OSL-3.0"
                ],
                "description": "Argento Breeze Themes",
                "support": {
                    "source": "https://github.com/swissup/argento-breeze/tree/2.2.0",
                    "issues": "https://github.com/swissup/argento-breeze/issues"
                }
            },
            {
                "name": "swissup/argento-breeze",
                "version": "2.2.1",
                "version_normalized": "2.2.1.0",
                "source": {
                    "type": "git",
                    "url": "git@github.com:swissup/argento-breeze.git",
                    "reference": "17a64640ac1d2e93ef0bc6f9a15a05d0458fc557"
                },
                "dist": {
                    "type": "zip",
                    "url": "https://api.github.com/repos/swissup/argento-breeze/zipball/17a64640ac1d2e93ef0bc6f9a15a05d0458fc557",
                    "reference": "17a64640ac1d2e93ef0bc6f9a15a05d0458fc557",
                    "shasum": ""
                },
                "require": {
                    "swissup/module-ajaxpro": "^1.6.35",
                    "swissup/module-ajaxsearch": "^1.13.15",
                    "swissup/module-amp": "^1.5.7",
                    "swissup/module-askit": "^1.13.3",
                    "swissup/module-attributepages": "^1.6.7",
                    "swissup/module-breeze": "^2.11.1",
                    "swissup/module-breeze-integrations": "^1.3.1",
                    "swissup/module-chat-gpt-assistant": "^1.0.1",
                    "swissup/module-compare": "^1.2.1",
                    "swissup/module-easy-slide": "^1.8.4",
                    "swissup/module-easybanner": "^1.9.13",
                    "swissup/module-easycatalogimg": "^1.5.2",
                    "swissup/module-easytabs": "^1.12.7",
                    "swissup/module-fblike": "^1.3.8",
                    "swissup/module-featured-attributes": "^1.1.7",
                    "swissup/module-gdpr": "^1.5.20",
                    "swissup/module-gdpr-askit": "^1.1.3",
                    "swissup/module-gdpr-reviewreminder": "^1.0.0",
                    "swissup/module-gdpr-testimonials": "^1.1.1",
                    "swissup/module-highlight": "^1.9.0",
                    "swissup/module-hover-gallery": "^1.3.11",
                    "swissup/module-hreflang": "^1.6.4",
                    "swissup/module-hreflang-import-export": "^1.0.1",
                    "swissup/module-navigationpro": "^1.17.7",
                    "swissup/module-pagespeed": "^1.7.21",
                    "swissup/module-pro-labels": "^1.7.5",
                    "swissup/module-pro-labels-configurable-product": "^1.0.1",
                    "swissup/module-quantity-switcher": "^1.1.19",
                    "swissup/module-reviewreminder": "^1.1.15",
                    "swissup/module-rich-snippets": "^1.7.1",
                    "swissup/module-seo-canonical": "^1.11.8",
                    "swissup/module-seo-core": "^1.3.9",
                    "swissup/module-seo-cross-links": "^1.1.12",
                    "swissup/module-seo-html-sitemap": "^1.1.18",
                    "swissup/module-seo-images": "^1.3.20",
                    "swissup/module-seo-pager": "^1.3.3",
                    "swissup/module-seo-templates": "^1.7.5",
                    "swissup/module-seo-urls": "^1.5.48",
                    "swissup/module-seo-xml-sitemap": "^1.1.15",
                    "swissup/module-sold-together": "^1.9.11",
                    "swissup/module-sold-together-email": "^1.0.0",
                    "swissup/module-sold-together-import-export": "^1.0.1",
                    "swissup/module-testimonials": "^1.3.10",
                    "swissup/theme-frontend-argentobreeze-blank": "^2.1.0",
                    "swissup/theme-frontend-argentobreeze-chic": "^2.0.3",
                    "swissup/theme-frontend-argentobreeze-force": "^2.0.8",
                    "swissup/theme-frontend-argentobreeze-stripes": "^2.0.3"
                },
                "time": "2023-12-08T11:56:55+00:00",
                "type": "metapackage",
                "extra": {
                    "marketplace": {
                        "gallery": [
                            "https://docs.swissuplabs.com/images/marketplace/theme-frontend-argento.png"
                        ],
                        "links": {
                            "docs": "https://docs.swissuplabs.com/m2/argento-breeze/",
                            "changelog": "https://docs.swissuplabs.com/m2/argento-breeze/changelog/"
                        }
                    }
                },
                "license": [
                    "OSL-3.0"
                ],
                "description": "Argento Breeze Themes",
                "support": {
                    "source": "https://github.com/swissup/argento-breeze/tree/2.2.1",
                    "issues": "https://github.com/swissup/argento-breeze/issues"
                }
            },
            {
                "name": "swissup/argento-breeze",
                "version": "2.2.2",
                "version_normalized": "2.2.2.0",
                "source": {
                    "type": "git",
                    "url": "git@github.com:swissup/argento-breeze.git",
                    "reference": "6f0b409254e8b42cfe1e46e43cf7226efe75a50e"
                },
                "dist": {
                    "type": "zip",
                    "url": "https://api.github.com/repos/swissup/argento-breeze/zipball/6f0b409254e8b42cfe1e46e43cf7226efe75a50e",
                    "reference": "6f0b409254e8b42cfe1e46e43cf7226efe75a50e",
                    "shasum": ""
                },
                "require": {
                    "swissup/module-ajaxpro": "^1.7.3",
                    "swissup/module-ajaxsearch": "^1.13.15",
                    "swissup/module-amp": "^1.5.7",
                    "swissup/module-askit": "^1.13.3",
                    "swissup/module-attributepages": "^1.6.8",
                    "swissup/module-breeze": "^2.13.1",
                    "swissup/module-breeze-integrations": "^1.3.2",
                    "swissup/module-chat-gpt-assistant": "^1.0.1",
                    "swissup/module-compare": "^1.2.3",
                    "swissup/module-easy-slide": "^1.8.4",
                    "swissup/module-easybanner": "^1.9.15",
                    "swissup/module-easycatalogimg": "^1.5.2",
                    "swissup/module-easytabs": "^1.12.8",
                    "swissup/module-fblike": "^1.3.9",
                    "swissup/module-featured-attributes": "^1.1.7",
                    "swissup/module-gdpr": "^1.5.23",
                    "swissup/module-gdpr-askit": "^1.1.3",
                    "swissup/module-gdpr-reviewreminder": "^1.0.0",
                    "swissup/module-gdpr-testimonials": "^1.1.1",
                    "swissup/module-highlight": "^1.9.1",
                    "swissup/module-hover-gallery": "^1.3.11",
                    "swissup/module-hreflang": "^1.6.4",
                    "swissup/module-hreflang-import-export": "^1.0.1",
                    "swissup/module-navigationpro": "^1.17.10",
                    "swissup/module-pagespeed": "^1.7.21",
                    "swissup/module-pro-labels": "^1.7.6",
                    "swissup/module-pro-labels-configurable-product": "^1.0.1",
                    "swissup/module-quantity-switcher": "^1.1.19",
                    "swissup/module-reviewreminder": "^1.1.16",
                    "swissup/module-rich-snippets": "^1.7.3",
                    "swissup/module-seo-canonical": "^1.11.9",
                    "swissup/module-seo-core": "^1.3.9",
                    "swissup/module-seo-cross-links": "^1.1.12",
                    "swissup/module-seo-html-sitemap": "^1.1.18",
                    "swissup/module-seo-images": "^1.3.20",
                    "swissup/module-seo-pager": "^1.3.3",
                    "swissup/module-seo-templates": "^1.7.6",
                    "swissup/module-seo-urls": "^1.5.48",
                    "swissup/module-seo-xml-sitemap": "^1.1.15",
                    "swissup/module-sold-together": "^1.9.14",
                    "swissup/module-sold-together-email": "^1.0.0",
                    "swissup/module-sold-together-import-export": "^1.0.1",
                    "swissup/module-testimonials": "^1.3.12",
                    "swissup/theme-frontend-argentobreeze-blank": "^2.1.0",
                    "swissup/theme-frontend-argentobreeze-chic": "^2.1.1",
                    "swissup/theme-frontend-argentobreeze-force": "^2.0.10",
                    "swissup/theme-frontend-argentobreeze-stripes": "^2.0.3"
                },
                "time": "2024-02-06T15:58:25+00:00",
                "type": "metapackage",
                "extra": {
                    "marketplace": {
                        "gallery": [
                            "https://docs.swissuplabs.com/images/marketplace/theme-frontend-argento.png"
                        ],
                        "links": {
                            "docs": "https://docs.swissuplabs.com/m2/argento-breeze/",
                            "changelog": "https://docs.swissuplabs.com/m2/argento-breeze/changelog/"
                        }
                    }
                },
                "license": [
                    "OSL-3.0"
                ],
                "description": "Argento Breeze Themes",
                "support": {
                    "source": "https://github.com/swissup/argento-breeze/tree/2.2.2",
                    "issues": "https://github.com/swissup/argento-breeze/issues"
                }
            },
            {
                "name": "swissup/argento-breeze",
                "version": "2.3.0",
                "version_normalized": "2.3.0.0",
                "source": {
                    "type": "git",
                    "url": "git@github.com:swissup/argento-breeze.git",
                    "reference": "45d7b8d696b36c4eced14343128f78d608973960"
                },
                "dist": {
                    "type": "zip",
                    "url": "https://api.github.com/repos/swissup/argento-breeze/zipball/45d7b8d696b36c4eced14343128f78d608973960",
                    "reference": "45d7b8d696b36c4eced14343128f78d608973960",
                    "shasum": ""
                },
                "require": {
                    "swissup/module-ajaxpro": "^1.7.4",
                    "swissup/module-ajaxsearch": "^1.13.15",
                    "swissup/module-amp": "^1.5.7",
                    "swissup/module-askit": "^1.14.1",
                    "swissup/module-attributepages": "^1.6.8",
                    "swissup/module-breeze": "^2.14.3",
                    "swissup/module-breeze-integrations": "^1.3.2",
                    "swissup/module-chat-gpt-assistant": "^1.0.1",
                    "swissup/module-compare": "^1.2.3",
                    "swissup/module-easy-slide": "^1.8.4",
                    "swissup/module-easybanner": "^1.9.17",
                    "swissup/module-easycatalogimg": "^1.5.3",
                    "swissup/module-easytabs": "^1.12.8",
                    "swissup/module-fblike": "^1.3.9",
                    "swissup/module-featured-attributes": "^1.1.7",
                    "swissup/module-gdpr": "^1.6.0",
                    "swissup/module-gdpr-askit": "^1.1.3",
                    "swissup/module-gdpr-reviewreminder": "^1.0.0",
                    "swissup/module-gdpr-testimonials": "^1.1.1",
                    "swissup/module-highlight": "^1.9.2",
                    "swissup/module-hover-gallery": "^1.3.11",
                    "swissup/module-hreflang": "^1.6.5",
                    "swissup/module-hreflang-import-export": "^1.0.1",
                    "swissup/module-navigationpro": "^1.17.11",
                    "swissup/module-pagespeed": "^1.7.22",
                    "swissup/module-pro-labels": "^1.7.6",
                    "swissup/module-pro-labels-configurable-product": "^1.0.1",
                    "swissup/module-quantity-switcher": "^1.1.19",
                    "swissup/module-reviewreminder": "^1.1.16",
                    "swissup/module-rich-snippets": "^1.7.3",
                    "swissup/module-seo-canonical": "^1.11.9",
                    "swissup/module-seo-core": "^1.3.9",
                    "swissup/module-seo-cross-links": "^1.1.12",
                    "swissup/module-seo-html-sitemap": "^1.1.18",
                    "swissup/module-seo-images": "^1.3.20",
                    "swissup/module-seo-pager": "^1.3.4",
                    "swissup/module-seo-templates": "^1.7.6",
                    "swissup/module-seo-urls": "^1.5.49",
                    "swissup/module-seo-xml-sitemap": "^1.1.15",
                    "swissup/module-sold-together": "^1.9.15",
                    "swissup/module-sold-together-email": "^1.0.0",
                    "swissup/module-sold-together-import-export": "^1.0.1",
                    "swissup/module-testimonials": "^1.3.12",
                    "swissup/theme-frontend-argentobreeze-blank": "^2.1.0",
                    "swissup/theme-frontend-argentobreeze-chic": "^2.1.4",
                    "swissup/theme-frontend-argentobreeze-force": "^2.0.11",
                    "swissup/theme-frontend-argentobreeze-stripes": "^2.0.4"
                },
                "time": "2024-03-07T10:30:26+00:00",
                "type": "metapackage",
                "extra": {
                    "marketplace": {
                        "gallery": [
                            "https://docs.swissuplabs.com/images/marketplace/theme-frontend-argento.png"
                        ],
                        "links": {
                            "docs": "https://docs.swissuplabs.com/m2/argento-breeze/",
                            "changelog": "https://docs.swissuplabs.com/m2/argento-breeze/changelog/"
                        }
                    }
                },
                "license": [
                    "OSL-3.0"
                ],
                "description": "Argento Breeze Themes",
                "support": {
                    "source": "https://github.com/swissup/argento-breeze/tree/2.3.0",
                    "issues": "https://github.com/swissup/argento-breeze/issues"
                }
            },
            {
                "name": "swissup/argento-breeze",
                "version": "2.3.1",
                "version_normalized": "2.3.1.0",
                "source": {
                    "type": "git",
                    "url": "git@github.com:swissup/argento-breeze.git",
                    "reference": "dee1ac35364a24a6fa6451d066f634a5630f4d03"
                },
                "dist": {
                    "type": "zip",
                    "url": "https://api.github.com/repos/swissup/argento-breeze/zipball/dee1ac35364a24a6fa6451d066f634a5630f4d03",
                    "reference": "dee1ac35364a24a6fa6451d066f634a5630f4d03",
                    "shasum": ""
                },
                "require": {
                    "swissup/module-ajaxpro": "^1.7.5",
                    "swissup/module-ajaxsearch": "^1.13.15",
                    "swissup/module-amp": "^1.5.7",
                    "swissup/module-askit": "^1.14.2",
                    "swissup/module-attributepages": "^1.6.11",
                    "swissup/module-breeze": "^2.14.3",
                    "swissup/module-breeze-integrations": "^1.3.2",
                    "swissup/module-chat-gpt-assistant": "^1.1.0",
                    "swissup/module-compare": "^1.2.3",
                    "swissup/module-easy-slide": "^1.8.8",
                    "swissup/module-easybanner": "^1.9.19",
                    "swissup/module-easycatalogimg": "^1.5.4",
                    "swissup/module-easytabs": "^1.12.9",
                    "swissup/module-fblike": "^1.3.9",
                    "swissup/module-featured-attributes": "^1.1.7",
                    "swissup/module-gdpr": "^1.6.3",
                    "swissup/module-gdpr-askit": "^1.1.3",
                    "swissup/module-gdpr-reviewreminder": "^1.0.0",
                    "swissup/module-gdpr-testimonials": "^1.1.1",
                    "swissup/module-highlight": "^1.9.5",
                    "swissup/module-hover-gallery": "^1.3.11",
                    "swissup/module-hreflang": "^1.6.6",
                    "swissup/module-hreflang-import-export": "^1.0.1",
                    "swissup/module-navigationpro": "^1.17.13",
                    "swissup/module-pagespeed": "^1.7.27",
                    "swissup/module-pro-labels": "^1.7.7",
                    "swissup/module-pro-labels-configurable-product": "^1.0.1",
                    "swissup/module-quantity-switcher": "^1.1.19",
                    "swissup/module-reviewreminder": "^1.1.16",
                    "swissup/module-rich-snippets": "^1.7.3",
                    "swissup/module-seo-canonical": "^1.11.9",
                    "swissup/module-seo-core": "^1.3.9",
                    "swissup/module-seo-cross-links": "^1.1.13",
                    "swissup/module-seo-html-sitemap": "^1.1.18",
                    "swissup/module-seo-images": "^1.3.20",
                    "swissup/module-seo-pager": "^1.3.5",
                    "swissup/module-seo-templates": "^1.7.7",
                    "swissup/module-seo-urls": "^1.5.50",
                    "swissup/module-seo-xml-sitemap": "^1.1.15",
                    "swissup/module-sold-together": "^1.9.16",
                    "swissup/module-sold-together-email": "^1.0.0",
                    "swissup/module-sold-together-import-export": "^1.0.1",
                    "swissup/module-testimonials": "^1.3.12",
                    "swissup/theme-frontend-argentobreeze-blank": "^2.1.0",
                    "swissup/theme-frontend-argentobreeze-chic": "^2.1.6",
                    "swissup/theme-frontend-argentobreeze-force": "^2.0.11",
                    "swissup/theme-frontend-argentobreeze-stripes": "^2.0.4"
                },
                "time": "2024-04-23T12:06:12+00:00",
                "type": "metapackage",
                "extra": {
                    "marketplace": {
                        "gallery": [
                            "https://docs.swissuplabs.com/images/marketplace/theme-frontend-argento.png"
                        ],
                        "links": {
                            "docs": "https://docs.swissuplabs.com/m2/argento-breeze/",
                            "changelog": "https://docs.swissuplabs.com/m2/argento-breeze/changelog/"
                        }
                    }
                },
                "license": [
                    "OSL-3.0"
                ],
                "description": "Argento Breeze Themes",
                "support": {
                    "source": "https://github.com/swissup/argento-breeze/tree/2.3.1",
                    "issues": "https://github.com/swissup/argento-breeze/issues"
                }
            },
            {
                "name": "swissup/argento-breeze",
                "version": "2.4.0",
                "version_normalized": "2.4.0.0",
                "source": {
                    "type": "git",
                    "url": "git@github.com:swissup/argento-breeze.git",
                    "reference": "d74cd6a1eb4aa58c083643b34f5d0ebe6811b39a"
                },
                "dist": {
                    "type": "zip",
                    "url": "https://api.github.com/repos/swissup/argento-breeze/zipball/d74cd6a1eb4aa58c083643b34f5d0ebe6811b39a",
                    "reference": "d74cd6a1eb4aa58c083643b34f5d0ebe6811b39a",
                    "shasum": ""
                },
                "require": {
                    "swissup/module-ajaxpro": "^1.7.7",
                    "swissup/module-ajaxsearch": "^1.13.15",
                    "swissup/module-amp": "^1.5.8",
                    "swissup/module-askit": "^1.14.2",
                    "swissup/module-attributepages": "^1.6.11",
                    "swissup/module-breeze": "^2.14.3",
                    "swissup/module-breeze-integrations": "^1.3.2",
                    "swissup/module-chat-gpt-assistant": "^1.1.0",
                    "swissup/module-compare": "^1.2.4",
                    "swissup/module-easy-slide": "^1.8.9",
                    "swissup/module-easybanner": "^1.9.19",
                    "swissup/module-easycatalogimg": "^1.5.6",
                    "swissup/module-easytabs": "^1.12.10",
                    "swissup/module-fblike": "^1.3.9",
                    "swissup/module-featured-attributes": "^1.1.7",
                    "swissup/module-gdpr": "^1.7.0",
                    "swissup/module-gdpr-askit": "^1.1.3",
                    "swissup/module-gdpr-reviewreminder": "^1.0.0",
                    "swissup/module-gdpr-testimonials": "^1.1.1",
                    "swissup/module-highlight": "^1.9.6",
                    "swissup/module-hover-gallery": "^1.3.11",
                    "swissup/module-hreflang": "^1.6.6",
                    "swissup/module-hreflang-import-export": "^1.0.1",
                    "swissup/module-navigationpro": "^1.17.13",
                    "swissup/module-pagespeed": "^1.7.28",
                    "swissup/module-pro-labels": "^1.7.7",
                    "swissup/module-pro-labels-configurable-product": "^1.0.1",
                    "swissup/module-quantity-switcher": "^1.1.19",
                    "swissup/module-reviewreminder": "^1.1.16",
                    "swissup/module-rich-snippets": "^1.7.3",
                    "swissup/module-seo-canonical": "^1.11.9",
                    "swissup/module-seo-core": "^1.3.9",
                    "swissup/module-seo-cross-links": "^1.1.13",
                    "swissup/module-seo-html-sitemap": "^1.1.18",
                    "swissup/module-seo-images": "^1.3.20",
                    "swissup/module-seo-pager": "^1.3.5",
                    "swissup/module-seo-templates": "^1.7.7",
                    "swissup/module-seo-urls": "^1.5.50",
                    "swissup/module-seo-xml-sitemap": "^1.1.15",
                    "swissup/module-sold-together": "^1.9.17",
                    "swissup/module-sold-together-email": "^1.0.0",
                    "swissup/module-sold-together-import-export": "^1.0.1",
                    "swissup/module-testimonials": "^1.3.13",
                    "swissup/theme-frontend-argentobreeze-blank": "^2.1.0",
                    "swissup/theme-frontend-argentobreeze-chic": "^2.4.0",
                    "swissup/theme-frontend-argentobreeze-force": "^2.4.0",
                    "swissup/theme-frontend-argentobreeze-stripes": "^2.4.0"
                },
                "time": "2024-05-09T08:22:24+00:00",
                "type": "metapackage",
                "extra": {
                    "marketplace": {
                        "gallery": [
                            "https://docs.swissuplabs.com/images/marketplace/theme-frontend-argento.png"
                        ],
                        "links": {
                            "docs": "https://docs.swissuplabs.com/m2/argento-breeze/",
                            "changelog": "https://docs.swissuplabs.com/m2/argento-breeze/changelog/"
                        }
                    }
                },
                "license": [
                    "OSL-3.0"
                ],
                "description": "Argento Breeze Themes",
                "support": {
                    "source": "https://github.com/swissup/argento-breeze/tree/2.4.0",
                    "issues": "https://github.com/swissup/argento-breeze/issues"
                }
            }
        ]
    }
}
